octobot_trading/__init__.pxd
octobot_trading/__init__.py
octobot_trading/constants.py
octobot_trading/enums.py
octobot_trading/errors.py
octobot_trading/exchange_channel.cpython-38-darwin.so
octobot_trading/exchange_channel.pxd
octobot_trading/exchange_channel.py
octobot_trading/octobot_channel_consumer.cpython-38-darwin.so
octobot_trading/octobot_channel_consumer.pxd
octobot_trading/octobot_channel_consumer.py
octobot_trading/api/__init__.py
octobot_trading/api/channels.py
octobot_trading/api/contracts.py
octobot_trading/api/exchange.py
octobot_trading/api/modes.py
octobot_trading/api/orders.py
octobot_trading/api/portfolio.py
octobot_trading/api/positions.py
octobot_trading/api/profitability.py
octobot_trading/api/storage.py
octobot_trading/api/symbol_data.py
octobot_trading/api/trader.py
octobot_trading/api/trades.py
octobot_trading/exchange_data/__init__.pxd
octobot_trading/exchange_data/__init__.py
octobot_trading/exchange_data/exchange_symbol_data.cpython-38-darwin.so
octobot_trading/exchange_data/exchange_symbol_data.pxd
octobot_trading/exchange_data/exchange_symbol_data.py
octobot_trading/exchange_data/exchange_symbols_data.cpython-38-darwin.so
octobot_trading/exchange_data/exchange_symbols_data.pxd
octobot_trading/exchange_data/exchange_symbols_data.py
octobot_trading/exchange_data/contracts/__init__.pxd
octobot_trading/exchange_data/contracts/__init__.py
octobot_trading/exchange_data/contracts/contract_factory.py
octobot_trading/exchange_data/contracts/future_contract.cpython-38-darwin.so
octobot_trading/exchange_data/contracts/future_contract.pxd
octobot_trading/exchange_data/contracts/future_contract.py
octobot_trading/exchange_data/contracts/margin_contract.cpython-38-darwin.so
octobot_trading/exchange_data/contracts/margin_contract.pxd
octobot_trading/exchange_data/contracts/margin_contract.py
octobot_trading/exchange_data/funding/__init__.pxd
octobot_trading/exchange_data/funding/__init__.py
OctoBot_Trading-2.3.39.dist-info/LICENSE
OctoBot_Trading-2.3.39.dist-info/METADATA
OctoBot_Trading-2.3.39.dist-info/WHEEL
OctoBot_Trading-2.3.39.dist-info/top_level.txt
OctoBot_Trading-2.3.39.dist-info/RECORD
