Metadata-Version: 2.1
Name: OctoBot-Trading
Version: 2.3.39
Summary: OctoBot project trading package
Home-page: https://github.com/Drakkar-Software/OctoBot-Trading
Author: Drakkar-Software
Author-email: drakkar-software@protonmail.com
License: LGPL-3.0
Classifier: Development Status :: 5 - Production/Stable
Classifier: Programming Language :: Python :: 3.8
Classifier: Programming Language :: Python :: 3.9
Classifier: Programming Language :: Cython
Classifier: Operating System :: OS Independent
Classifier: Operating System :: MacOS :: MacOS X
Classifier: Operating System :: Microsoft :: Windows
Classifier: Operating System :: POSIX
Requires-Python: >=3.8
License-File: LICENSE
Requires-Dist: cython (==0.29.32)
Requires-Dist: numpy (==1.24.0)
Requires-Dist: OctoBot-Backtesting (<1.9,>=1.8)
Requires-Dist: Async-Channel (<2.2,>=2.1)
Requires-Dist: OctoBot-Commons (<1.9,>=1.8)
Requires-Dist: OctoBot-Tentacles-Manager (<2.9,>=2.8)
Requires-Dist: trading-backend (>=1.0.19)
Requires-Dist: ccxt (==3.0.74)
Requires-Dist: cryptography
Requires-Dist: sortedcontainers (==2.4.0)
Requires-Dist: tinydb (==4.5.2)
